penvy/PenvyConfig.py
penvy/bash/BashProfileCreator.py
penvy/check/CheckInterface.py
penvy/check/ChecksRunner.py
penvy/cli/argument_parser.py
penvy/cli/str2bool.py
penvy/cmd/detector.py
penvy/conda/ActivateCondaEnvCall.py
penvy/conda/CondaEnvironmentCreator.py
penvy/conda/CondaExecutablePathFinder.py
penvy/conda/CondaPathsResolver.py
penvy/conda/CondaScriptsCreator.py
penvy/conda/CondaVersionCheck.py
penvy/conda/CondaVersionGetter.py
penvy/conda/SourceCondaAppender.py
penvy/conda/activate.d/env_vars.sh
penvy/conda/conda_executable_paths.txt
penvy/conda/deactivate.d/env_vars.sh
penvy/conda/possible_executable_paths.py
penvy/container/dicontainer.py
penvy/container/diservice.py
penvy/container/init.py
penvy/dotenv/DotEnvCreator.py
penvy/env/EnvConfig.py
penvy/env/EnvInitRunner.py
penvy/filesystem/rmdir.py
penvy/git/GitVersionCheck.py
penvy/git/PostMergeHookCreator.py
penvy/init.py
penvy/libroot.py
penvy/logger/LoggerLevelResolver.py
penvy/logger/colorlog/__init__.py
penvy/logger/colorlog/colorlog.py
penvy/logger/colorlog/escape_codes.py
penvy/logger/colorlog/logging.py
penvy/logger/logger_factory.py
penvy/parameters/ParametersMerger.py
penvy/parameters/ParametersResolverInterface.py
penvy/parameters/ResolvedParametersBuilder.py
penvy/poetry/DependenciesInstallHookCreator.py
penvy/poetry/DependenciesInstaller.py
penvy/poetry/DependenciesLoader.py
penvy/poetry/PoetryBinUnixPathAppender.py
penvy/poetry/PoetryBinWindowsPathAppender.py
penvy/poetry/PoetryHomeResolver.py
penvy/poetry/PoetryInstaller.py
penvy/poetry/PoetryPathResolver.py
penvy/poetry/PyprojectChecker.py
penvy/poetry/PyprojectLoader.py
penvy/poetry/config_reader.py
penvy/python/PythonExecutablePathResolver.py
penvy/setup/SetupRunner.py
penvy/setup/SetupStepInterface.py
penvy/shell/PyfonyEnvCreator.py
penvy/shell/ShellCheck.py
penvy/shell/ShellFileCreator.py
penvy/shell/ShellResolver.py
penvy/shell/SourcePyfonyEnvAppender.py
penvy/shell/VerbosityResolver.py
penvy/shell/detector.py
penvy-1.4.3.dist-info/METADATA
penvy-1.4.3.dist-info/WHEEL
penvy-1.4.3.dist-info/entry_points.txt
penvy-1.4.3.dist-info/RECORD
