Metadata-Version: 2.1
Name: penvy
Version: 1.4.3
Summary: Pyfony framework development environment initializer
Home-page: https://github.com/pyfony/penvy
License: MIT
Author: Jiri Koutny
Author-email: jiri.koutny@datasentics.com
Requires-Python: >=3.7,<4.0
Classifier: License :: OSI Approved :: MIT License
Classifier: Operating System :: OS Independent
Classifier: Programming Language :: Python :: 3
Classifier: Programming Language :: Python :: 3.7
Classifier: Programming Language :: Python :: 3.8
Classifier: Programming Language :: Python :: 3.9
Classifier: Programming Language :: Python :: 3.10
Classifier: Programming Language :: Python :: 3.11
Project-URL: Repository, https://github.com/pyfony/penvy
